dffml_model_tensorflow/__init__.py
dffml_model_tensorflow/dnnc.py
dffml_model_tensorflow/dnnr.py
dffml_model_tensorflow/version.py
dffml_model_tensorflow/util/__init__.py
dffml_model_tensorflow/util/config/__init__.py
dffml_model_tensorflow/util/config/tensorflow.py
tests/__init__.py
tests/test_dnnc.py
tests/test_dnnr.py
tests/test_tf_integration.py
tests/util/__init__.py
tests/util/test_config.py
dffml_model_tensorflow-0.3.0.post0.dist-info/LICENSE
dffml_model_tensorflow-0.3.0.post0.dist-info/METADATA
dffml_model_tensorflow-0.3.0.post0.dist-info/WHEEL
dffml_model_tensorflow-0.3.0.post0.dist-info/entry_points.txt
dffml_model_tensorflow-0.3.0.post0.dist-info/top_level.txt
dffml_model_tensorflow-0.3.0.post0.dist-info/RECORD
